odoo10_addon_stock_picking_package_preparation-10.0.1.0.2-py2.7-nspkg.pth
odoo/addons/stock_picking_package_preparation/README.rst
odoo/addons/stock_picking_package_preparation/__init__.py
odoo/addons/stock_picking_package_preparation/__manifest__.py
odoo/addons/stock_picking_package_preparation/i18n/de.po
odoo/addons/stock_picking_package_preparation/i18n/en.po
odoo/addons/stock_picking_package_preparation/i18n/es.po
odoo/addons/stock_picking_package_preparation/i18n/fr.po
odoo/addons/stock_picking_package_preparation/i18n/it.po
odoo/addons/stock_picking_package_preparation/i18n/nl_NL.po
odoo/addons/stock_picking_package_preparation/i18n/sl.po
odoo/addons/stock_picking_package_preparation/i18n/stock_picking_package_preparation.pot
odoo/addons/stock_picking_package_preparation/models/__init__.py
odoo/addons/stock_picking_package_preparation/models/stock_picking_package_preparation.py
odoo/addons/stock_picking_package_preparation/security/ir.model.access.csv
odoo/addons/stock_picking_package_preparation/security/package_preparation_security.xml
odoo/addons/stock_picking_package_preparation/tests/__init__.py
odoo/addons/stock_picking_package_preparation/tests/test_package_preparation.py
odoo/addons/stock_picking_package_preparation/views/stock_picking_package_preparation_view.xml
odoo10_addon_stock_picking_package_preparation-10.0.1.0.2.dist-info/METADATA
odoo10_addon_stock_picking_package_preparation-10.0.1.0.2.dist-info/RECORD
odoo10_addon_stock_picking_package_preparation-10.0.1.0.2.dist-info/WHEEL
odoo10_addon_stock_picking_package_preparation-10.0.1.0.2.dist-info/namespace_packages.txt
odoo10_addon_stock_picking_package_preparation-10.0.1.0.2.dist-info/top_level.txt
